LICENSE
MANIFEST.in
README.md
pyproject.toml
setup.py
GPTQModel.egg-info/PKG-INFO
GPTQModel.egg-info/SOURCES.txt
GPTQModel.egg-info/dependency_links.txt
GPTQModel.egg-info/entry_points.txt
GPTQModel.egg-info/requires.txt
GPTQModel.egg-info/top_level.txt
gptqmodel/__init__.py
gptqmodel/version.py
gptqmodel/adapter/__init__.py
gptqmodel/adapter/adapter.py
gptqmodel/adapter/peft.py
gptqmodel/adapter/remote.py
gptqmodel/cli/__init__.py
gptqmodel/cli/env.py
gptqmodel/cli/gptqmodel.py
gptqmodel/eora/__init__.py
gptqmodel/eora/eora.py
gptqmodel/hf_minimax_m2/__init__.py
gptqmodel/hf_minimax_m2/configuration_minimax_m2.py
gptqmodel/hf_minimax_m2/modeling_minimax_m2.py
gptqmodel/hf_minimax_m2/test_minimax_m2_hf.py
gptqmodel/looper/__init__.py
gptqmodel/looper/awq_processor.py
gptqmodel/looper/dequantize_processor.py
gptqmodel/looper/eora_processor.py
gptqmodel/looper/gptq_processor.py
gptqmodel/looper/input_cache.py
gptqmodel/looper/loop_processor.py
gptqmodel/looper/module_looper.py
gptqmodel/looper/named_module.py
gptqmodel/looper/native_processor.py
gptqmodel/looper/qqq_processor.py
gptqmodel/looper/stage_inputs_capture.py
gptqmodel/looper/stage_layer.py
gptqmodel/looper/stage_subset.py
gptqmodel/looper/tensorparallel_weight_processor.py
gptqmodel/models/__init__.py
gptqmodel/models/_const.py
gptqmodel/models/auto.py
gptqmodel/models/base.py
gptqmodel/models/loader.py
gptqmodel/models/writer.py
gptqmodel/models/definitions/__init__.py
gptqmodel/models/definitions/afmoe.py
gptqmodel/models/definitions/apertus.py
gptqmodel/models/definitions/baichuan.py
gptqmodel/models/definitions/bailing_moe.py
gptqmodel/models/definitions/base_qwen2_5_omni.py
gptqmodel/models/definitions/base_qwen2_vl.py
gptqmodel/models/definitions/base_qwen3_vl.py
gptqmodel/models/definitions/bloom.py
gptqmodel/models/definitions/brumby.py
gptqmodel/models/definitions/chatglm.py
gptqmodel/models/definitions/codegen.py
gptqmodel/models/definitions/dbrx.py
gptqmodel/models/definitions/dbrx_converted.py
gptqmodel/models/definitions/decilm.py
gptqmodel/models/definitions/deepseek_v2.py
gptqmodel/models/definitions/deepseek_v3.py
gptqmodel/models/definitions/dots1.py
