Metadata-Version: 2.4
Name: GPTQModel
Version: 5.6.6
Summary: Production ready LLM model compression/quantization toolkit with hw accelerated inference support for both cpu/gpu via HF, vLLM, and SGLang.
Author-email: ModelCloud <qubitium@modelcloud.ai>
License-Expression: Apache-2.0
Project-URL: Homepage, https://github.com/ModelCloud/GPTQModel
Keywords: gptq,awq,qqq,autogptq,autoawq,eora,gar,quantization,large-language-models,transformers,llm,moe,compression
Classifier: Programming Language :: Python :: 3
Classifier: Programming Language :: Python :: 3.10
Classifier: Programming Language :: Python :: 3.11
Classifier: Programming Language :: Python :: 3.12
Classifier: Programming Language :: Python :: 3.13
Classifier: Programming Language :: Python :: 3.14
Classifier: Programming Language :: C++
Classifier: Intended Audience :: Developers
Classifier: Intended Audience :: Education
Classifier: Intended Audience :: Science/Research
Classifier: Intended Audience :: Information Technology
Classifier: Topic :: Scientific/Engineering :: Artificial Intelligence
Classifier: Topic :: Scientific/Engineering :: Information Analysis
Requires-Python: >=3.10
License-File: LICENSE
Requires-Dist: accelerate>=1.10.1
Requires-Dist: numpy==2.2.6
Requires-Dist: torch>=2.8.0
Requires-Dist: safetensors>=0.6.2
Requires-Dist: transformers>=4.57.1
Requires-Dist: threadpoolctl>=3.6.0
Requires-Dist: packaging>=24.2
Requires-Dist: device-smi>=0.5.3
Requires-Dist: protobuf>=6.32.0
Requires-Dist: pillow>=11.3.0
Requires-Dist: hf_transfer>=0.1.9
Requires-Dist: huggingface_hub>=0.34.4
Requires-Dist: tokenicer>=0.0.5
Requires-Dist: logbar>=0.1.9
Requires-Dist: maturin>=1.9.4
Requires-Dist: datasets>=3.6.0
Requires-Dist: pyarrow>=21.0
Requires-Dist: dill>=0.3.8
Requires-Dist: pypcre>=0.2.8
Requires-Dist: torchao>=0.14.1
Requires-Dist: kernels>=0.11.1
Provides-Extra: test
Requires-Dist: pytest>=8.3.5; extra == "test"
Requires-Dist: pytest-timeout>=2.3.1; extra == "test"
Requires-Dist: parameterized; extra == "test"
Provides-Extra: quality
Requires-Dist: ruff==0.13.0; extra == "quality"
Provides-Extra: vllm
Requires-Dist: vllm>=0.10.2; extra == "vllm"
Requires-Dist: flashinfer-python>=0.3.1; extra == "vllm"
Provides-Extra: sglang
Requires-Dist: sglang[srt]>=0.4.6; extra == "sglang"
Requires-Dist: flashinfer-python>=0.3.1; extra == "sglang"
Provides-Extra: bitblas
Requires-Dist: bitblas==0.1.0.post1; extra == "bitblas"
Provides-Extra: hf
Requires-Dist: optimum>=1.21.2; extra == "hf"
Provides-Extra: eval
Requires-Dist: lm_eval>=0.4.7; extra == "eval"
Requires-Dist: evalplus>=0.3.1; extra == "eval"
Provides-Extra: triton
Requires-Dist: triton>=3.4.0; extra == "triton"
Provides-Extra: openai
Requires-Dist: uvicorn; extra == "openai"
Requires-Dist: fastapi; extra == "openai"
Requires-Dist: pydantic; extra == "openai"
Provides-Extra: mlx
Requires-Dist: mlx_lm>=0.24.0; extra == "mlx"
Dynamic: license-file
